ergup/__init__.py
ergup/ergup.py
ergup-0.1.0.dist-info/METADATA
ergup-0.1.0.dist-info/WHEEL
ergup-0.1.0.dist-info/entry_points.txt
ergup-0.1.0.dist-info/top_level.txt
ergup-0.1.0.dist-info/RECORD
