Metadata-Version: 2.2
Name: ergup
Version: 0.1.0
Summary: Erg toolchain installer
Home-page: https://github.com/mtshiba/ergup
Author: Shunsuke Shibayama
Author-email: Shunsuke Shibayama <sbym1346@gmail.com>
License: MIT
Classifier: Programming Language :: Python :: 3
Classifier: License :: OSI Approved :: MIT License
Classifier: Operating System :: OS Independent
Requires-Python: >=3.7
Dynamic: author
Dynamic: home-page
